deep_lynx/__init__.py
deep_lynx/api_client.py
deep_lynx/configuration.py
deep_lynx/rest.py
deep_lynx/api/__init__.py
deep_lynx/api/authentication_api.py
deep_lynx/api/containers_api.py
deep_lynx/api/data_export_api.py
deep_lynx/api/data_query_api.py
deep_lynx/api/data_sources_api.py
deep_lynx/api/data_targets_api.py
deep_lynx/api/data_type_mappings_api.py
deep_lynx/api/default_api.py
deep_lynx/api/events_api.py
deep_lynx/api/graph_api.py
deep_lynx/api/imports_api.py
deep_lynx/api/metatype_keys_api.py
deep_lynx/api/metatype_relationship_keys_api.py
deep_lynx/api/metatype_relationship_pairs_api.py
deep_lynx/api/metatype_relationships_api.py
deep_lynx/api/metatypes_api.py
deep_lynx/api/misc_api.py
deep_lynx/api/tags_api.py
deep_lynx/api/tasks_api.py
deep_lynx/api/time_series_api.py
deep_lynx/api/users_api.py
deep_lynx/models/__init__.py
deep_lynx/models/add_data_to_import_response.py
deep_lynx/models/assign_role_request.py
deep_lynx/models/batch_container_update_request.py
deep_lynx/models/batch_container_update_request_inner.py
deep_lynx/models/batch_update_container_response.py
deep_lynx/models/container.py
deep_lynx/models/container_config.py
deep_lynx/models/container_id_data_source_templates_body.py
deep_lynx/models/container_import_request.py
deep_lynx/models/container_import_response.py
deep_lynx/models/container_import_update_response.py
deep_lynx/models/container_invite.py
deep_lynx/models/containerscontainer_iddata_source_templates_custom_fields.py
deep_lynx/models/create_container_request.py
deep_lynx/models/create_container_response.py
deep_lynx/models/create_data_export_request.py
deep_lynx/models/create_data_source_config.py
deep_lynx/models/create_data_source_request.py
deep_lynx/models/create_data_sources_response.py
deep_lynx/models/create_data_target_config.py
deep_lynx/models/create_data_target_request.py
deep_lynx/models/create_data_targets_response.py
deep_lynx/models/create_event_action_request.py
deep_lynx/models/create_event_action_response.py
deep_lynx-0.1.8.dist-info/LICENSE.txt
deep_lynx-0.1.8.dist-info/METADATA
deep_lynx-0.1.8.dist-info/NOTICE.txt
deep_lynx-0.1.8.dist-info/WHEEL
deep_lynx-0.1.8.dist-info/top_level.txt
deep_lynx-0.1.8.dist-info/RECORD
