Metadata-Version: 2.1
Name: deep_lynx
Version: 0.1.8
Summary: Deep Lynx Python SDK
Home-page: https://github.com/idaholab/Deep-Lynx-Python-Package
Author: Jeren Browning
Author-email: jeren.browning@inl.gov
License: MIT
Keywords: Swagger,Deep Lynx
License-File: LICENSE.txt
License-File: NOTICE.txt
Requires-Dist: urllib3 >=1.15
Requires-Dist: six >=1.10
Requires-Dist: certifi
Requires-Dist: python-dateutil
